ckeditor5/__init__.py
ckeditor5/fields.py
ckeditor5/widgets.py
ckeditor5/migrations/__init__.py
ckeditor5/static/ckeditor5/ckeditor-init.js
ckeditor5/static/ckeditor5/typography.scss
ckeditor5/static/ckeditor5/ckeditor_build_classic/LICENSE.md
ckeditor5/static/ckeditor5/ckeditor_build_classic/README.md
ckeditor5/static/ckeditor5/ckeditor_build_classic/ckeditor.js
ckeditor5/static/ckeditor5/ckeditor_build_classic/ckeditor.js.map
ckeditor5/static/ckeditor5/ckeditor_build_classic/translations/ar.js
ckeditor5/static/ckeditor5/ckeditor_build_classic/translations/ast.js
ckeditor5/static/ckeditor5/ckeditor_build_classic/translations/bg.js
ckeditor5/static/ckeditor5/ckeditor_build_classic/translations/ca.js
ckeditor5/static/ckeditor5/ckeditor_build_classic/translations/cs.js
ckeditor5/static/ckeditor5/ckeditor_build_classic/translations/da.js
ckeditor5/static/ckeditor5/ckeditor_build_classic/translations/de-ch.js
ckeditor5/static/ckeditor5/ckeditor_build_classic/translations/de.js
ckeditor5/static/ckeditor5/ckeditor_build_classic/translations/el.js
ckeditor5/static/ckeditor5/ckeditor_build_classic/translations/en-au.js
ckeditor5/static/ckeditor5/ckeditor_build_classic/translations/eo.js
ckeditor5/static/ckeditor5/ckeditor_build_classic/translations/es.js
ckeditor5/static/ckeditor5/ckeditor_build_classic/translations/et.js
ckeditor5/static/ckeditor5/ckeditor_build_classic/translations/eu.js
ckeditor5/static/ckeditor5/ckeditor_build_classic/translations/fa.js
ckeditor5/static/ckeditor5/ckeditor_build_classic/translations/fi.js
ckeditor5/static/ckeditor5/ckeditor_build_classic/translations/fr.js
ckeditor5/static/ckeditor5/ckeditor_build_classic/translations/gl.js
ckeditor5/static/ckeditor5/ckeditor_build_classic/translations/gu.js
ckeditor5/static/ckeditor5/ckeditor_build_classic/translations/hr.js
ckeditor5/static/ckeditor5/ckeditor_build_classic/translations/hu.js
ckeditor5/static/ckeditor5/ckeditor_build_classic/translations/it.js
django_ckeditor5-0.0.3.dist-info/METADATA
django_ckeditor5-0.0.3.dist-info/WHEEL
django_ckeditor5-0.0.3.dist-info/top_level.txt
django_ckeditor5-0.0.3.dist-info/RECORD
