Metadata-Version: 2.1
Name: django-ckeditor5
Version: 0.0.3
Summary: Django CKEditor 5 集成
Home-page: https://github.com/n37r06u3/django-ckeditor5
Author: n37r06u3
Author-email: n37r06u3@gmail.com
License: UNKNOWN
Platform: UNKNOWN
Classifier: Programming Language :: Python
Classifier: Programming Language :: Python :: 2.7
Classifier: Programming Language :: Python :: 3.3
Classifier: Programming Language :: Python :: 3.4
Classifier: Programming Language :: Python :: 3.5
Classifier: Programming Language :: Python :: 3.6
Classifier: License :: OSI Approved :: BSD License
Classifier: Operating System :: OS Independent
Classifier: Framework :: Django
Classifier: Intended Audience :: Developers
Classifier: Topic :: Internet :: WWW/HTTP :: Dynamic Content
Requires-Dist: django
Requires-Dist: django-js-asset
